odoo/addons/project_merge/README.rst
odoo/addons/project_merge/__init__.py
odoo/addons/project_merge/__manifest__.py
odoo/addons/project_merge/i18n/it.po
odoo/addons/project_merge/i18n/project_merge.pot
odoo/addons/project_merge/readme/CONTRIBUTORS.md
odoo/addons/project_merge/readme/DESCRIPTION.md
odoo/addons/project_merge/readme/USAGE.md
odoo/addons/project_merge/security/ir.model.access.csv
odoo/addons/project_merge/static/description/icon.png
odoo/addons/project_merge/static/description/index.html
odoo/addons/project_merge/tests/__init__.py
odoo/addons/project_merge/tests/test_project_task_merge.py
odoo/addons/project_merge/wizard/__init__.py
odoo/addons/project_merge/wizard/project_task_merge.py
odoo/addons/project_merge/wizard/project_task_merge_views.xml
odoo_addon_project_merge-18.0.1.0.0.2.dist-info/METADATA
odoo_addon_project_merge-18.0.1.0.0.2.dist-info/WHEEL
odoo_addon_project_merge-18.0.1.0.0.2.dist-info/top_level.txt
odoo_addon_project_merge-18.0.1.0.0.2.dist-info/RECORD
